flam.py
setup.cfg
setup.py
flam.egg-info/PKG-INFO
flam.egg-info/SOURCES.txt
flam.egg-info/dependency_links.txt
flam.egg-info/requires.txt
flam.egg-info/top_level.txt