Metadata-Version: 1.0
Name: flam
Version: 0.6
Summary: A minimalist Python application framework.
Home-page: http://github.com/alecthomas/flam
Author: Alec Thomas
Author-email: alec@swapoff.org
License: BSD
Download-URL: http://github.com/alecthomas/flam
Platform: any
